pymembrane/__init__.py
pymembrane/__version__.py
pymembrane/__pycache__/__init__.cpython-312.pyc
pymembrane/__pycache__/__init__.cpython-39.pyc
pymembrane/__pycache__/__version__.cpython-312.pyc
pymembrane/__pycache__/__version__.cpython-39.pyc
pymembrane/__pycache__/membrane.cpython-39.pyc
pymembrane/config/__colors__.py
pymembrane/config/__config__.py
pymembrane/config/__disp__.py
pymembrane/config/pymembrane.json
pymembrane/config/__pycache__/__colors__.cpython-312.pyc
pymembrane/config/__pycache__/__colors__.cpython-39.pyc
pymembrane/config/__pycache__/__config__.cpython-312.pyc
pymembrane/config/__pycache__/__config__.cpython-39.pyc
pymembrane/config/__pycache__/__disp__.cpython-312.pyc
pymembrane/config/__pycache__/__disp__.cpython-39.pyc
pymembrane/membrane/__init__.py
pymembrane/membrane/membrane.py
pymembrane/membrane/__pycache__/__init__.cpython-312.pyc
pymembrane/membrane/__pycache__/__init__.cpython-39.pyc
pymembrane/membrane/__pycache__/membrane.cpython-312.pyc
pymembrane/membrane/__pycache__/membrane.cpython-39.pyc
pymembrane-0.0.4.dist-info/LICENSE
pymembrane-0.0.4.dist-info/METADATA
pymembrane-0.0.4.dist-info/WHEEL
pymembrane-0.0.4.dist-info/top_level.txt
pymembrane-0.0.4.dist-info/RECORD
